{"nodes": [{"id": "d_github_repos_telegram_signal_copier_tools_log_monitor_agent_py", "label": "log_monitor_agent.py", "file_type": "code", "source_file": "D:\\Github repos\\Telegram signal Copier\\tools\\log_monitor_agent.py", "source_location": "L1"}, {"id": "tools_log_monitor_agent_tail", "label": "_tail()", "file_type": "code", "source_file": "D:\\Github repos\\Telegram signal Copier\\tools\\log_monitor_agent.py", "source_location": "L66"}, {"id": "tools_log_monitor_agent_recent_lines", "label": "_recent_lines()", "file_type": "code", "source_file": "D:\\Github repos\\Telegram signal Copier\\tools\\log_monitor_agent.py", "source_location": "L80"}, {"id": "tools_log_monitor_agent_restart_listener", "label": "_restart_listener()", "file_type": "code", "source_file": "D:\\Github repos\\Telegram signal Copier\\tools\\log_monitor_agent.py", "source_location": "L98"}, {"id": "tools_log_monitor_agent_clear_stale_cmds", "label": "_clear_stale_cmds()", "file_type": "code", "source_file": "D:\\Github repos\\Telegram signal Copier\\tools\\log_monitor_agent.py", "source_location": "L121"}, {"id": "tools_log_monitor_agent_logmonitoragent", "label": "LogMonitorAgent", "file_type": "code", "source_file": "D:\\Github repos\\Telegram signal Copier\\tools\\log_monitor_agent.py", "source_location": "L139"}, {"id": "tools_log_monitor_agent_logmonitoragent_init", "label": ".__init__()", "file_type": "code", "source_file": "D:\\Github repos\\Telegram signal Copier\\tools\\log_monitor_agent.py", "source_location": "L140"}, {"id": "tools_log_monitor_agent_logmonitoragent_log_sources", "label": "._log_sources()", "file_type": "code", "source_file": "D:\\Github repos\\Telegram signal Copier\\tools\\log_monitor_agent.py", "source_location": "L160"}, {"id": "tools_log_monitor_agent_logmonitoragent_run_once", "label": ".run_once()", "file_type": "code", "source_file": "D:\\Github repos\\Telegram signal Copier\\tools\\log_monitor_agent.py", "source_location": "L167"}, {"id": "tools_log_monitor_agent_logmonitoragent_run_daemon", "label": ".run_daemon()", "file_type": "code", "source_file": "D:\\Github repos\\Telegram signal Copier\\tools\\log_monitor_agent.py", "source_location": "L290"}, {"id": "tools_log_monitor_agent_main", "label": "main()", "file_type": "code", "source_file": "D:\\Github repos\\Telegram signal Copier\\tools\\log_monitor_agent.py", "source_location": "L315"}, {"id": "tools_log_monitor_agent_rationale_81", "label": "Return only lines whose timestamp falls within the last window_seconds.", "file_type": "rationale", "source_file": "D:\\Github repos\\Telegram signal Copier\\tools\\log_monitor_agent.py", "source_location": "L81"}, {"id": "tools_log_monitor_agent_rationale_161", "label": "All log files to monitor.", "file_type": "rationale", "source_file": "D:\\Github repos\\Telegram signal Copier\\tools\\log_monitor_agent.py", "source_location": "L161"}], "edges": [{"source": "d_github_repos_telegram_signal_copier_tools_log_monitor_agent_py", "target": "argparse", "relation": "imports", "context": "import", "confidence": "EXTRACTED", "source_file": "D:\\Github repos\\Telegram signal Copier\\tools\\log_monitor_agent.py", "source_location": "L20", "weight": 1.0}, {"source": "d_github_repos_telegram_signal_copier_tools_log_monitor_agent_py", "target": "logging", "relation": "imports", "context": "import", "confidence": "EXTRACTED", "source_file": "D:\\Github repos\\Telegram signal Copier\\tools\\log_monitor_agent.py", "source_location": "L21", "weight": 1.0}, {"source": "d_github_repos_telegram_signal_copier_tools_log_monitor_agent_py", "target": "os", "relation": "imports", "context": "import", "confidence": "EXTRACTED", "source_file": "D:\\Github repos\\Telegram signal Copier\\tools\\log_monitor_agent.py", "source_location": "L22", "weight": 1.0}, {"source": "d_github_repos_telegram_signal_copier_tools_log_monitor_agent_py", "target": "re", "relation": "imports", "context": "import", "confidence": "EXTRACTED", "source_file": "D:\\Github repos\\Telegram signal Copier\\tools\\log_monitor_agent.py", "source_location": "L23", "weight": 1.0}, {"source": "d_github_repos_telegram_signal_copier_tools_log_monitor_agent_py", "target": "subprocess", "relation": "imports", "context": "import", "confidence": "EXTRACTED", "source_file": "D:\\Github repos\\Telegram signal Copier\\tools\\log_monitor_agent.py", "source_location": "L24", "weight": 1.0}, {"source": "d_github_repos_telegram_signal_copier_tools_log_monitor_agent_py", "target": "sys", "relation": "imports", "context": "import", "confidence": "EXTRACTED", "source_file": "D:\\Github repos\\Telegram signal Copier\\tools\\log_monitor_agent.py", "source_location": "L25", "weight": 1.0}, {"source": "d_github_repos_telegram_signal_copier_tools_log_monitor_agent_py", "target": "time", "relation": "imports", "context": "import", "confidence": "EXTRACTED", "source_file": "D:\\Github repos\\Telegram signal Copier\\tools\\log_monitor_agent.py", "source_location": "L26", "weight": 1.0}, {"source": "d_github_repos_telegram_signal_copier_tools_log_monitor_agent_py", "target": "pathlib", "relation": "imports_from", "context": "import", "confidence": "EXTRACTED", "source_file": "D:\\Github repos\\Telegram signal Copier\\tools\\log_monitor_agent.py", "source_location": "L27", "weight": 1.0}, {"source": "d_github_repos_telegram_signal_copier_tools_log_monitor_agent_py", "target": "collections", "relation": "imports_from", "context": "import", "confidence": "EXTRACTED", "source_file": "D:\\Github repos\\Telegram signal Copier\\tools\\log_monitor_agent.py", "source_location": "L28", "weight": 1.0}, {"source": "d_github_repos_telegram_signal_copier_tools_log_monitor_agent_py", "target": "datetime", "relation": "imports_from", "context": "import", "confidence": "EXTRACTED", "source_file": "D:\\Github repos\\Telegram signal Copier\\tools\\log_monitor_agent.py", "source_location": "L29", "weight": 1.0}, {"source": "d_github_repos_telegram_signal_copier_tools_log_monitor_agent_py", "target": "tools_log_monitor_agent_tail", "relation": "contains", "confidence": "EXTRACTED", "source_file": "D:\\Github repos\\Telegram signal Copier\\tools\\log_monitor_agent.py", "source_location": "L66", "weight": 1.0}, {"source": "d_github_repos_telegram_signal_copier_tools_log_monitor_agent_py", "target": "tools_log_monitor_agent_recent_lines", "relation": "contains", "confidence": "EXTRACTED", "source_file": "D:\\Github repos\\Telegram signal Copier\\tools\\log_monitor_agent.py", "source_location": "L80", "weight": 1.0}, {"source": "d_github_repos_telegram_signal_copier_tools_log_monitor_agent_py", "target": "tools_log_monitor_agent_restart_listener", "relation": "contains", "confidence": "EXTRACTED", "source_file": "D:\\Github repos\\Telegram signal Copier\\tools\\log_monitor_agent.py", "source_location": "L98", "weight": 1.0}, {"source": "d_github_repos_telegram_signal_copier_tools_log_monitor_agent_py", "target": "tools_log_monitor_agent_clear_stale_cmds", "relation": "contains", "confidence": "EXTRACTED", "source_file": "D:\\Github repos\\Telegram signal Copier\\tools\\log_monitor_agent.py", "source_location": "L121", "weight": 1.0}, {"source": "d_github_repos_telegram_signal_copier_tools_log_monitor_agent_py", "target": "tools_log_monitor_agent_logmonitoragent", "relation": "contains", "confidence": "EXTRACTED", "source_file": "D:\\Github repos\\Telegram signal Copier\\tools\\log_monitor_agent.py", "source_location": "L139", "weight": 1.0}, {"source": "tools_log_monitor_agent_logmonitoragent", "target": "tools_log_monitor_agent_logmonitoragent_init", "relation": "method", "confidence": "EXTRACTED", "source_file": "D:\\Github repos\\Telegram signal Copier\\tools\\log_monitor_agent.py", "source_location": "L140", "weight": 1.0}, {"source": "tools_log_monitor_agent_logmonitoragent", "target": "tools_log_monitor_agent_logmonitoragent_log_sources", "relation": "method", "confidence": "EXTRACTED", "source_file": "D:\\Github repos\\Telegram signal Copier\\tools\\log_monitor_agent.py", "source_location": "L160", "weight": 1.0}, {"source": "tools_log_monitor_agent_logmonitoragent", "target": "tools_log_monitor_agent_logmonitoragent_run_once", "relation": "method", "confidence": "EXTRACTED", "source_file": "D:\\Github repos\\Telegram signal Copier\\tools\\log_monitor_agent.py", "source_location": "L167", "weight": 1.0}, {"source": "tools_log_monitor_agent_logmonitoragent", "target": "tools_log_monitor_agent_logmonitoragent_run_daemon", "relation": "method", "confidence": "EXTRACTED", "source_file": "D:\\Github repos\\Telegram signal Copier\\tools\\log_monitor_agent.py", "source_location": "L290", "weight": 1.0}, {"source": "d_github_repos_telegram_signal_copier_tools_log_monitor_agent_py", "target": "tools_log_monitor_agent_main", "relation": "contains", "confidence": "EXTRACTED", "source_file": "D:\\Github repos\\Telegram signal Copier\\tools\\log_monitor_agent.py", "source_location": "L315", "weight": 1.0}, {"source": "tools_log_monitor_agent_logmonitoragent_run_once", "target": "tools_log_monitor_agent_logmonitoragent_log_sources", "relation": "calls", "context": "call", "confidence": "EXTRACTED", "source_file": "D:\\Github repos\\Telegram signal Copier\\tools\\log_monitor_agent.py", "source_location": "L180", "weight": 1.0}, {"source": "tools_log_monitor_agent_logmonitoragent_run_once", "target": "tools_log_monitor_agent_tail", "relation": "calls", "context": "call", "confidence": "EXTRACTED", "source_file": "D:\\Github repos\\Telegram signal Copier\\tools\\log_monitor_agent.py", "source_location": "L181", "weight": 1.0}, {"source": "tools_log_monitor_agent_logmonitoragent_run_once", "target": "tools_log_monitor_agent_recent_lines", "relation": "calls", "context": "call", "confidence": "EXTRACTED", "source_file": "D:\\Github repos\\Telegram signal Copier\\tools\\log_monitor_agent.py", "source_location": "L182", "weight": 1.0}, {"source": "tools_log_monitor_agent_logmonitoragent_run_once", "target": "tools_log_monitor_agent_clear_stale_cmds", "relation": "calls", "context": "call", "confidence": "EXTRACTED", "source_file": "D:\\Github repos\\Telegram signal Copier\\tools\\log_monitor_agent.py", "source_location": "L235", "weight": 1.0}, {"source": "tools_log_monitor_agent_logmonitoragent_run_once", "target": "tools_log_monitor_agent_restart_listener", "relation": "calls", "context": "call", "confidence": "EXTRACTED", "source_file": "D:\\Github repos\\Telegram signal Copier\\tools\\log_monitor_agent.py", "source_location": "L281", "weight": 1.0}, {"source": "tools_log_monitor_agent_logmonitoragent_run_daemon", "target": "tools_log_monitor_agent_logmonitoragent_log_sources", "relation": "calls", "context": "call", "confidence": "EXTRACTED", "source_file": "D:\\Github repos\\Telegram signal Copier\\tools\\log_monitor_agent.py", "source_location": "L297", "weight": 1.0}, {"source": "tools_log_monitor_agent_logmonitoragent_run_daemon", "target": "tools_log_monitor_agent_logmonitoragent_run_once", "relation": "calls", "context": "call", "confidence": "EXTRACTED", "source_file": "D:\\Github repos\\Telegram signal Copier\\tools\\log_monitor_agent.py", "source_location": "L303", "weight": 1.0}, {"source": "tools_log_monitor_agent_main", "target": "tools_log_monitor_agent_logmonitoragent", "relation": "calls", "context": "call", "confidence": "EXTRACTED", "source_file": "D:\\Github repos\\Telegram signal Copier\\tools\\log_monitor_agent.py", "source_location": "L325", "weight": 1.0}, {"source": "tools_log_monitor_agent_main", "target": "tools_log_monitor_agent_logmonitoragent_run_once", "relation": "calls", "context": "call", "confidence": "EXTRACTED", "source_file": "D:\\Github repos\\Telegram signal Copier\\tools\\log_monitor_agent.py", "source_location": "L333", "weight": 1.0}, {"source": "tools_log_monitor_agent_main", "target": "tools_log_monitor_agent_logmonitoragent_run_daemon", "relation": "calls", "context": "call", "confidence": "EXTRACTED", "source_file": "D:\\Github repos\\Telegram signal Copier\\tools\\log_monitor_agent.py", "source_location": "L335", "weight": 1.0}, {"source": "tools_log_monitor_agent_rationale_81", "target": "tools_log_monitor_agent_recent_lines", "relation": "rationale_for", "confidence": "EXTRACTED", "source_file": "D:\\Github repos\\Telegram signal Copier\\tools\\log_monitor_agent.py", "source_location": "L81", "weight": 1.0}, {"source": "tools_log_monitor_agent_rationale_161", "target": "tools_log_monitor_agent_logmonitoragent_log_sources", "relation": "rationale_for", "confidence": "EXTRACTED", "source_file": "D:\\Github repos\\Telegram signal Copier\\tools\\log_monitor_agent.py", "source_location": "L161", "weight": 1.0}], "raw_calls": [{"caller_nid": "tools_log_monitor_agent_tail", "callee": "exists", "is_member_call": true, "source_file": "D:\\Github repos\\Telegram signal Copier\\tools\\log_monitor_agent.py", "source_location": "L67"}, {"caller_nid": "tools_log_monitor_agent_tail", "callee": "open", "is_member_call": true, "source_file": "D:\\Github repos\\Telegram signal Copier\\tools\\log_monitor_agent.py", "source_location": "L70"}, {"caller_nid": "tools_log_monitor_agent_tail", "callee": "seek", "is_member_call": true, "source_file": "D:\\Github repos\\Telegram signal Copier\\tools\\log_monitor_agent.py", "source_location": "L71"}, {"caller_nid": "tools_log_monitor_agent_tail", "callee": "tell", "is_member_call": true, "source_file": "D:\\Github repos\\Telegram signal Copier\\tools\\log_monitor_agent.py", "source_location": "L72"}, {"caller_nid": "tools_log_monitor_agent_tail", "callee": "seek", "is_member_call": true, "source_file": "D:\\Github repos\\Telegram signal Copier\\tools\\log_monitor_agent.py", "source_location": "L73"}, {"caller_nid": "tools_log_monitor_agent_tail", "callee": "max", "is_member_call": false, "source_file": "D:\\Github repos\\Telegram signal Copier\\tools\\log_monitor_agent.py", "source_location": "L73"}, {"caller_nid": "tools_log_monitor_agent_tail", "callee": "read", "is_member_call": true, "source_file": "D:\\Github repos\\Telegram signal Copier\\tools\\log_monitor_agent.py", "source_location": "L74"}, {"caller_nid": "tools_log_monitor_agent_tail", "callee": "splitlines", "is_member_call": true, "source_file": "D:\\Github repos\\Telegram signal Copier\\tools\\log_monitor_agent.py", "source_location": "L75"}, {"caller_nid": "tools_log_monitor_agent_tail", "callee": "decode", "is_member_call": true, "source_file": "D:\\Github repos\\Telegram signal Copier\\tools\\log_monitor_agent.py", "source_location": "L75"}, {"caller_nid": "tools_log_monitor_agent_recent_lines", "callee": "time", "is_member_call": true, "source_file": "D:\\Github repos\\Telegram signal Copier\\tools\\log_monitor_agent.py", "source_location": "L82"}, {"caller_nid": "tools_log_monitor_agent_recent_lines", "callee": "len", "is_member_call": false, "source_file": "D:\\Github repos\\Telegram signal Copier\\tools\\log_monitor_agent.py", "source_location": "L85"}, {"caller_nid": "tools_log_monitor_agent_recent_lines", "callee": "timestamp", "is_member_call": true, "source_file": "D:\\Github repos\\Telegram signal Copier\\tools\\log_monitor_agent.py", "source_location": "L88"}, {"caller_nid": "tools_log_monitor_agent_recent_lines", "callee": "replace", "is_member_call": true, "source_file": "D:\\Github repos\\Telegram signal Copier\\tools\\log_monitor_agent.py", "source_location": "L88"}, {"caller_nid": "tools_log_monitor_agent_recent_lines", "callee": "strptime", "is_member_call": true, "source_file": "D:\\Github repos\\Telegram signal Copier\\tools\\log_monitor_agent.py", "source_location": "L88"}, {"caller_nid": "tools_log_monitor_agent_recent_lines", "callee": "append", "is_member_call": true, "source_file": "D:\\Github repos\\Telegram signal Copier\\tools\\log_monitor_agent.py", "source_location": "L92"}, {"caller_nid": "tools_log_monitor_agent_restart_listener", "callee": "run", "is_member_call": true, "source_file": "D:\\Github repos\\Telegram signal Copier\\tools\\log_monitor_agent.py", "source_location": "L104"}, {"caller_nid": "tools_log_monitor_agent_restart_listener", "callee": "str", "is_member_call": false, "source_file": "D:\\Github repos\\Telegram signal Copier\\tools\\log_monitor_agent.py", "source_location": "L105"}, {"caller_nid": "tools_log_monitor_agent_restart_listener", "callee": "str", "is_member_call": false, "source_file": "D:\\Github repos\\Telegram signal Copier\\tools\\log_monitor_agent.py", "source_location": "L106"}, {"caller_nid": "tools_log_monitor_agent_restart_listener", "callee": "info", "is_member_call": true, "source_file": "D:\\Github repos\\Telegram signal Copier\\tools\\log_monitor_agent.py", "source_location": "L111"}, {"caller_nid": "tools_log_monitor_agent_restart_listener", "callee": "info", "is_member_call": true, "source_file": "D:\\Github repos\\Telegram signal Copier\\tools\\log_monitor_agent.py", "source_location": "L114"}, {"caller_nid": "tools_log_monitor_agent_restart_listener", "callee": "warning", "is_member_call": true, "source_file": "D:\\Github repos\\Telegram signal Copier\\tools\\log_monitor_agent.py", "source_location": "L117"}, {"caller_nid": "tools_log_monitor_agent_clear_stale_cmds", "callee": "time", "is_member_call": true, "source_file": "D:\\Github repos\\Telegram signal Copier\\tools\\log_monitor_agent.py", "source_location": "L123"}, {"caller_nid": "tools_log_monitor_agent_clear_stale_cmds", "callee": "glob", "is_member_call": true, "source_file": "D:\\Github repos\\Telegram signal Copier\\tools\\log_monitor_agent.py", "source_location": "L124"}, {"caller_nid": "tools_log_monitor_agent_clear_stale_cmds", "callee": "stat", "is_member_call": true, "source_file": "D:\\Github repos\\Telegram signal Copier\\tools\\log_monitor_agent.py", "source_location": "L126"}, {"caller_nid": "tools_log_monitor_agent_clear_stale_cmds", "callee": "unlink", "is_member_call": true, "source_file": "D:\\Github repos\\Telegram signal Copier\\tools\\log_monitor_agent.py", "source_location": "L127"}, {"caller_nid": "tools_log_monitor_agent_clear_stale_cmds", "callee": "info", "is_member_call": true, "source_file": "D:\\Github repos\\Telegram signal Copier\\tools\\log_monitor_agent.py", "source_location": "L128"}, {"caller_nid": "tools_log_monitor_agent_logmonitoragent_init", "callee": "deque", "is_member_call": false, "source_file": "D:\\Github repos\\Telegram signal Copier\\tools\\log_monitor_agent.py", "source_location": "L157"}, {"caller_nid": "tools_log_monitor_agent_logmonitoragent_run_once", "callee": "strftime", "is_member_call": true, "source_file": "D:\\Github repos\\Telegram signal Copier\\tools\\log_monitor_agent.py", "source_location": "L169"}, {"caller_nid": "tools_log_monitor_agent_logmonitoragent_run_once", "callee": "now", "is_member_call": true, "source_file": "D:\\Github repos\\Telegram signal Copier\\tools\\log_monitor_agent.py", "source_location": "L169"}, {"caller_nid": "tools_log_monitor_agent_logmonitoragent_run_once", "callee": "time", "is_member_call": true, "source_file": "D:\\Github repos\\Telegram signal Copier\\tools\\log_monitor_agent.py", "source_location": "L176"}, {"caller_nid": "tools_log_monitor_agent_logmonitoragent_run_once", "callee": "extend", "is_member_call": true, "source_file": "D:\\Github repos\\Telegram signal Copier\\tools\\log_monitor_agent.py", "source_location": "L182"}, {"caller_nid": "tools_log_monitor_agent_logmonitoragent_run_once", "callee": "max", "is_member_call": false, "source_file": "D:\\Github repos\\Telegram signal Copier\\tools\\log_monitor_agent.py", "source_location": "L182"}, {"caller_nid": "tools_log_monitor_agent_logmonitoragent_run_once", "callee": "reversed", "is_member_call": false, "source_file": "D:\\Github repos\\Telegram signal Copier\\tools\\log_monitor_agent.py", "source_location": "L185"}, {"caller_nid": "tools_log_monitor_agent_logmonitoragent_run_once", "callee": "search", "is_member_call": true, "source_file": "D:\\Github repos\\Telegram signal Copier\\tools\\log_monitor_agent.py", "source_location": "L186"}, {"caller_nid": "tools_log_monitor_agent_logmonitoragent_run_once", "callee": "int", "is_member_call": false, "source_file": "D:\\Github repos\\Telegram signal Copier\\tools\\log_monitor_agent.py", "source_location": "L188"}, {"caller_nid": "tools_log_monitor_agent_logmonitoragent_run_once", "callee": "group", "is_member_call": true, "source_file": "D:\\Github repos\\Telegram signal Copier\\tools\\log_monitor_agent.py", "source_location": "L188"}, {"caller_nid": "tools_log_monitor_agent_logmonitoragent_run_once", "callee": "strftime", "is_member_call": true, "source_file": "D:\\Github repos\\Telegram signal Copier\\tools\\log_monitor_agent.py", "source_location": "L192"}, {"caller_nid": "tools_log_monitor_agent_logmonitoragent_run_once", "callee": "fromtimestamp", "is_member_call": true, "source_file": "D:\\Github repos\\Telegram signal Copier\\tools\\log_monitor_agent.py", "source_location": "L192"}, {"caller_nid": "tools_log_monitor_agent_logmonitoragent_run_once", "callee": "warning", "is_member_call": true, "source_file": "D:\\Github repos\\Telegram signal Copier\\tools\\log_monitor_agent.py", "source_location": "L194"}, {"caller_nid": "tools_log_monitor_agent_logmonitoragent_run_once", "callee": "append", "is_member_call": true, "source_file": "D:\\Github repos\\Telegram signal Copier\\tools\\log_monitor_agent.py", "source_location": "L196"}, {"caller_nid": "tools_log_monitor_agent_logmonitoragent_run_once", "callee": "search", "is_member_call": true, "source_file": "D:\\Github repos\\Telegram signal Copier\\tools\\log_monitor_agent.py", "source_location": "L202"}, {"caller_nid": "tools_log_monitor_agent_logmonitoragent_run_once", "callee": "timestamp", "is_member_call": true, "source_file": "D:\\Github repos\\Telegram signal Copier\\tools\\log_monitor_agent.py", "source_location": "L204"}, {"caller_nid": "tools_log_monitor_agent_logmonitoragent_run_once", "callee": "replace", "is_member_call": true, "source_file": "D:\\Github repos\\Telegram signal Copier\\tools\\log_monitor_agent.py", "source_location": "L204"}, {"caller_nid": "tools_log_monitor_agent_logmonitoragent_run_once", "callee": "strptime", "is_member_call": true, "source_file": "D:\\Github repos\\Telegram signal Copier\\tools\\log_monitor_agent.py", "source_location": "L204"}, {"caller_nid": "tools_log_monitor_agent_logmonitoragent_run_once", "callee": "append", "is_member_call": true, "source_file": "D:\\Github repos\\Telegram signal Copier\\tools\\log_monitor_agent.py", "source_location": "L208"}, {"caller_nid": "tools_log_monitor_agent_logmonitoragent_run_once", "callee": "len", "is_member_call": false, "source_file": "D:\\Github repos\\Telegram signal Copier\\tools\\log_monitor_agent.py", "source_location": "L212"}, {"caller_nid": "tools_log_monitor_agent_logmonitoragent_run_once", "callee": "len", "is_member_call": false, "source_file": "D:\\Github repos\\Telegram signal Copier\\tools\\log_monitor_agent.py", "source_location": "L214"}, {"caller_nid": "tools_log_monitor_agent_logmonitoragent_run_once", "callee": "warning", "is_member_call": true, "source_file": "D:\\Github repos\\Telegram signal Copier\\tools\\log_monitor_agent.py", "source_location": "L215"}, {"caller_nid": "tools_log_monitor_agent_logmonitoragent_run_once", "callee": "append", "is_member_call": true, "source_file": "D:\\Github repos\\Telegram signal Copier\\tools\\log_monitor_agent.py", "source_location": "L216"}, {"caller_nid": "tools_log_monitor_agent_logmonitoragent_run_once", "callee": "min", "is_member_call": false, "source_file": "D:\\Github repos\\Telegram signal Copier\\tools\\log_monitor_agent.py", "source_location": "L218"}, {"caller_nid": "tools_log_monitor_agent_logmonitoragent_run_once", "callee": "info", "is_member_call": true, "source_file": "D:\\Github repos\\Telegram signal Copier\\tools\\log_monitor_agent.py", "source_location": "L219"}, {"caller_nid": "tools_log_monitor_agent_logmonitoragent_run_once", "callee": "max", "is_member_call": false, "source_file": "D:\\Github repos\\Telegram signal Copier\\tools\\log_monitor_agent.py", "source_location": "L222"}, {"caller_nid": "tools_log_monitor_agent_logmonitoragent_run_once", "callee": "search", "is_member_call": true, "source_file": "D:\\Github repos\\Telegram signal Copier\\tools\\log_monitor_agent.py", "source_location": "L225"}, {"caller_nid": "tools_log_monitor_agent_logmonitoragent_run_once", "callee": "len", "is_member_call": false, "source_file": "D:\\Github repos\\Telegram signal Copier\\tools\\log_monitor_agent.py", "source_location": "L228"}, {"caller_nid": "tools_log_monitor_agent_logmonitoragent_run_once", "callee": "info", "is_member_call": true, "source_file": "D:\\Github repos\\Telegram signal Copier\\tools\\log_monitor_agent.py", "source_location": "L229"}, {"caller_nid": "tools_log_monitor_agent_logmonitoragent_run_once", "callee": "append", "is_member_call": true, "source_file": "D:\\Github repos\\Telegram signal Copier\\tools\\log_monitor_agent.py", "source_location": "L230"}, {"caller_nid": "tools_log_monitor_agent_logmonitoragent_run_once", "callee": "info", "is_member_call": true, "source_file": "D:\\Github repos\\Telegram signal Copier\\tools\\log_monitor_agent.py", "source_location": "L238"}, {"caller_nid": "tools_log_monitor_agent_logmonitoragent_run_once", "callee": "append", "is_member_call": true, "source_file": "D:\\Github repos\\Telegram signal Copier\\tools\\log_monitor_agent.py", "source_location": "L240"}, {"caller_nid": "tools_log_monitor_agent_logmonitoragent_run_once", "callee": "dict", "is_member_call": false, "source_file": "D:\\Github repos\\Telegram signal Copier\\tools\\log_monitor_agent.py", "source_location": "L246"}, {"caller_nid": "tools_log_monitor_agent_logmonitoragent_run_once", "callee": "split", "is_member_call": true, "source_file": "D:\\Github repos\\Telegram signal Copier\\tools\\log_monitor_agent.py", "source_location": "L247"}, {"caller_nid": "tools_log_monitor_agent_logmonitoragent_run_once", "callee": "splitlines", "is_member_call": true, "source_file": "D:\\Github repos\\Telegram signal Copier\\tools\\log_monitor_agent.py", "source_location": "L248"}, {"caller_nid": "tools_log_monitor_agent_logmonitoragent_run_once", "callee": "read_text", "is_member_call": true, "source_file": "D:\\Github repos\\Telegram signal Copier\\tools\\log_monitor_agent.py", "source_location": "L248"}, {"caller_nid": "tools_log_monitor_agent_logmonitoragent_run_once", "callee": "float", "is_member_call": false, "source_file": "D:\\Github repos\\Telegram signal Copier\\tools\\log_monitor_agent.py", "source_location": "L251"}, {"caller_nid": "tools_log_monitor_agent_logmonitoragent_run_once", "callee": "get", "is_member_call": true, "source_file": "D:\\Github repos\\Telegram signal Copier\\tools\\log_monitor_agent.py", "source_location": "L251"}, {"caller_nid": "tools_log_monitor_agent_logmonitoragent_run_once", "callee": "warning", "is_member_call": true, "source_file": "D:\\Github repos\\Telegram signal Copier\\tools\\log_monitor_agent.py", "source_location": "L259"}, {"caller_nid": "tools_log_monitor_agent_logmonitoragent_run_once", "callee": "info", "is_member_call": true, "source_file": "D:\\Github repos\\Telegram signal Copier\\tools\\log_monitor_agent.py", "source_location": "L261"}, {"caller_nid": "tools_log_monitor_agent_logmonitoragent_run_once", "callee": "int", "is_member_call": false, "source_file": "D:\\Github repos\\Telegram signal Copier\\tools\\log_monitor_agent.py", "source_location": "L270"}, {"caller_nid": "tools_log_monitor_agent_logmonitoragent_run_once", "callee": "warning", "is_member_call": true, "source_file": "D:\\Github repos\\Telegram signal Copier\\tools\\log_monitor_agent.py", "source_location": "L272"}, {"caller_nid": "tools_log_monitor_agent_logmonitoragent_run_once", "callee": "append", "is_member_call": true, "source_file": "D:\\Github repos\\Telegram signal Copier\\tools\\log_monitor_agent.py", "source_location": "L273"}, {"caller_nid": "tools_log_monitor_agent_logmonitoragent_run_once", "callee": "int", "is_member_call": false, "source_file": "D:\\Github repos\\Telegram signal Copier\\tools\\log_monitor_agent.py", "source_location": "L275"}, {"caller_nid": "tools_log_monitor_agent_logmonitoragent_run_once", "callee": "info", "is_member_call": true, "source_file": "D:\\Github repos\\Telegram signal Copier\\tools\\log_monitor_agent.py", "source_location": "L276"}, {"caller_nid": "tools_log_monitor_agent_logmonitoragent_run_once", "callee": "append", "is_member_call": true, "source_file": "D:\\Github repos\\Telegram signal Copier\\tools\\log_monitor_agent.py", "source_location": "L277"}, {"caller_nid": "tools_log_monitor_agent_logmonitoragent_run_once", "callee": "info", "is_member_call": true, "source_file": "D:\\Github repos\\Telegram signal Copier\\tools\\log_monitor_agent.py", "source_location": "L280"}, {"caller_nid": "tools_log_monitor_agent_logmonitoragent_run_once", "callee": "append", "is_member_call": true, "source_file": "D:\\Github repos\\Telegram signal Copier\\tools\\log_monitor_agent.py", "source_location": "L285"}, {"caller_nid": "tools_log_monitor_agent_logmonitoragent_run_once", "callee": "print", "is_member_call": false, "source_file": "D:\\Github repos\\Telegram signal Copier\\tools\\log_monitor_agent.py", "source_location": "L287"}, {"caller_nid": "tools_log_monitor_agent_logmonitoragent_run_daemon", "callee": "info", "is_member_call": true, "source_file": "D:\\Github repos\\Telegram signal Copier\\tools\\log_monitor_agent.py", "source_location": "L291"}, {"caller_nid": "tools_log_monitor_agent_logmonitoragent_run_daemon", "callee": "print", "is_member_call": false, "source_file": "D:\\Github repos\\Telegram signal Copier\\tools\\log_monitor_agent.py", "source_location": "L296"}, {"caller_nid": "tools_log_monitor_agent_logmonitoragent_run_daemon", "callee": "print", "is_member_call": false, "source_file": "D:\\Github repos\\Telegram signal Copier\\tools\\log_monitor_agent.py", "source_location": "L297"}, {"caller_nid": "tools_log_monitor_agent_logmonitoragent_run_daemon", "callee": "str", "is_member_call": false, "source_file": "D:\\Github repos\\Telegram signal Copier\\tools\\log_monitor_agent.py", "source_location": "L297"}, {"caller_nid": "tools_log_monitor_agent_logmonitoragent_run_daemon", "callee": "exception", "is_member_call": true, "source_file": "D:\\Github repos\\Telegram signal Copier\\tools\\log_monitor_agent.py", "source_location": "L305"}, {"caller_nid": "tools_log_monitor_agent_logmonitoragent_run_daemon", "callee": "sleep", "is_member_call": true, "source_file": "D:\\Github repos\\Telegram signal Copier\\tools\\log_monitor_agent.py", "source_location": "L306"}, {"caller_nid": "tools_log_monitor_agent_logmonitoragent_run_daemon", "callee": "info", "is_member_call": true, "source_file": "D:\\Github repos\\Telegram signal Copier\\tools\\log_monitor_agent.py", "source_location": "L308"}, {"caller_nid": "tools_log_monitor_agent_logmonitoragent_run_daemon", "callee": "print", "is_member_call": false, "source_file": "D:\\Github repos\\Telegram signal Copier\\tools\\log_monitor_agent.py", "source_location": "L310"}, {"caller_nid": "tools_log_monitor_agent_main", "callee": "ArgumentParser", "is_member_call": true, "source_file": "D:\\Github repos\\Telegram signal Copier\\tools\\log_monitor_agent.py", "source_location": "L316"}, {"caller_nid": "tools_log_monitor_agent_main", "callee": "add_argument", "is_member_call": true, "source_file": "D:\\Github repos\\Telegram signal Copier\\tools\\log_monitor_agent.py", "source_location": "L317"}, {"caller_nid": "tools_log_monitor_agent_main", "callee": "add_argument", "is_member_call": true, "source_file": "D:\\Github repos\\Telegram signal Copier\\tools\\log_monitor_agent.py", "source_location": "L318"}, {"caller_nid": "tools_log_monitor_agent_main", "callee": "add_argument", "is_member_call": true, "source_file": "D:\\Github repos\\Telegram signal Copier\\tools\\log_monitor_agent.py", "source_location": "L319"}, {"caller_nid": "tools_log_monitor_agent_main", "callee": "add_argument", "is_member_call": true, "source_file": "D:\\Github repos\\Telegram signal Copier\\tools\\log_monitor_agent.py", "source_location": "L320"}, {"caller_nid": "tools_log_monitor_agent_main", "callee": "add_argument", "is_member_call": true, "source_file": "D:\\Github repos\\Telegram signal Copier\\tools\\log_monitor_agent.py", "source_location": "L321"}, {"caller_nid": "tools_log_monitor_agent_main", "callee": "add_argument", "is_member_call": true, "source_file": "D:\\Github repos\\Telegram signal Copier\\tools\\log_monitor_agent.py", "source_location": "L322"}, {"caller_nid": "tools_log_monitor_agent_main", "callee": "parse_args", "is_member_call": true, "source_file": "D:\\Github repos\\Telegram signal Copier\\tools\\log_monitor_agent.py", "source_location": "L323"}, {"caller_nid": "tools_log_monitor_agent_main", "callee": "print_help", "is_member_call": true, "source_file": "D:\\Github repos\\Telegram signal Copier\\tools\\log_monitor_agent.py", "source_location": "L337"}]}